pandocmk/__init__.py
pandocmk/cli.py
pandocmk/core.py
pandocmk/metadata.py
pandocmk/utils.py
pandocmk/version.py
pandocmk/view.py
pandocmk/watch.py
pandocmk-0.2.1.dist-info/LICENSE
pandocmk-0.2.1.dist-info/METADATA
pandocmk-0.2.1.dist-info/WHEEL
pandocmk-0.2.1.dist-info/entry_points.txt
pandocmk-0.2.1.dist-info/top_level.txt
pandocmk-0.2.1.dist-info/RECORD
