Metadata-Version: 2.1
Name: pandocmk
Version: 0.2.1
Summary: A minimalistic make for pandoc
Home-page: https://github.com/sergiocorreia/pandocmk
Author: Sergio Correia
Author-email: sergio.correia@gmail.com
License: MIT
Keywords: pandoc panflute markdown latex
Platform: UNKNOWN
Classifier: Development Status :: 3 - Alpha
Classifier: Environment :: Console
Classifier: Intended Audience :: End Users/Desktop
Classifier: Intended Audience :: Developers
Classifier: Topic :: Software Development :: Build Tools
Classifier: License :: OSI Approved :: BSD License
Classifier: Operating System :: OS Independent
Classifier: Topic :: Text Processing :: Filters
Classifier: Programming Language :: Python :: 3.7
Classifier: Programming Language :: Python :: 3.8
Classifier: Programming Language :: Python :: Implementation :: CPython
Requires-Python: >=3.7
Requires-Dist: panflute
Requires-Dist: watchdog
